{
  "schema_version": 3,
  "ts": "2026-05-16T09:27:15.286Z",
  "bucket_start_utc": "2026-05-16T09:00:00.000Z",
  "bucket_end_utc": "2026-05-16T12:00:00.000Z",
  "bucket_hours": 3,
  "source": {
    "type": "github_issues",
    "owner": "mowlsint",
    "repo": "MagicPaws",
    "state": "open"
  },
  "counts": {
    "open_events_total": 700,
    "open_events_deduped_total": 694,
    "recent_72h_events": 177,
    "recent_72h_deduped_events": 177,
    "recent_72h_source_capped_weighted_events": 47.15,
    "current_bucket_events": 0,
    "current_bucket_deduped_events": 0,
    "current_bucket_source_capped_weighted_events": 0,
    "duplicate_events_total": 6,
    "duplicate_events_72h": 0,
    "duplicate_events_bucket": 0,
    "social_rss_events_72h": 177,
    "social_rss_deduped_events_72h": 177,
    "social_rss_events_bucket": 0,
    "social_rss_deduped_events_bucket": 0,
    "p0_suspect_72h": 0,
    "geo_total": 0,
    "geo_72h": 0,
    "geo_count_method": "explicit_coordinates_only"
  },
  "sensors": {
    "hybrid_seismograph_pct": 42,
    "keyword_barometer_pct": 0,
    "government_weirdness": {
      "north_sea_pct": 14,
      "baltic_sea_pct": 10
    }
  },
  "diagnostics": {
    "scoring_input_note": "Sensor scores use deduped events plus source caps. Raw counts remain available for baseline analysis.",
    "source_cap_profile": {
      "social": [
        1,
        0.45,
        0.2,
        0.08
      ],
      "rss": [
        1,
        0.65,
        0.35,
        0.15
      ],
      "media": [
        1,
        0.75,
        0.5,
        0.25
      ],
      "official": [
        1,
        0.9,
        0.75,
        0.5
      ],
      "osint": [
        1,
        0.6,
        0.3,
        0.12
      ],
      "unknown": [
        1,
        0.5,
        0.2,
        0.08
      ]
    },
    "hybrid_weighted_points_72h": 49.89,
    "keyword_weighted_hits_bucket": 0,
    "keyword_raw_hits_bucket": 0,
    "keyword_scored_events_bucket": 0,
    "government_weirdness_north_sea_points": 6.48,
    "government_weirdness_baltic_sea_points": 4.68,
    "government_weirdness_north_sea_events": 13,
    "government_weirdness_baltic_sea_events": 11,
    "government_weirdness_north_sea_weighted_events": 5.15,
    "government_weirdness_baltic_sea_weighted_events": 3.7,
    "keyword_config_loaded": true,
    "keyword_config_version": 2,
    "cold_start_note": "Scores are cold-start density values until a 90-day baseline exists."
  },
  "top_terms": [],
  "top_sources_72h": [
    {
      "source_id": "The Maritime Executive",
      "count": 45
    },
    {
      "source_id": "small_wars_journal_rss",
      "count": 30
    },
    {
      "source_id": "gcaptain_rss",
      "count": 23
    },
    {
      "source_id": "cepa_feed",
      "count": 13
    },
    {
      "source_id": "die_flaschenpost_aussenpolitik_rss",
      "count": 10
    },
    {
      "source_id": "gids_feed",
      "count": 10
    },
    {
      "source_id": "rusi_latest_publications",
      "count": 9
    },
    {
      "source_id": "atlantic_council_reports",
      "count": 9
    },
    {
      "source_id": "swp_publications_de",
      "count": 8
    },
    {
      "source_id": "gCaptain",
      "count": 7
    },
    {
      "source_id": "swp_publications_en",
      "count": 5
    },
    {
      "source_id": "rusi_latest_commentary",
      "count": 5
    }
  ],
  "top_sources_72h_deduped": [
    {
      "source_id": "The Maritime Executive",
      "count": 45
    },
    {
      "source_id": "small_wars_journal_rss",
      "count": 30
    },
    {
      "source_id": "gcaptain_rss",
      "count": 23
    },
    {
      "source_id": "cepa_feed",
      "count": 13
    },
    {
      "source_id": "die_flaschenpost_aussenpolitik_rss",
      "count": 10
    },
    {
      "source_id": "gids_feed",
      "count": 10
    },
    {
      "source_id": "rusi_latest_publications",
      "count": 9
    },
    {
      "source_id": "atlantic_council_reports",
      "count": 9
    },
    {
      "source_id": "swp_publications_de",
      "count": 8
    },
    {
      "source_id": "gCaptain",
      "count": 7
    },
    {
      "source_id": "swp_publications_en",
      "count": 5
    },
    {
      "source_id": "rusi_latest_commentary",
      "count": 5
    }
  ],
  "domain_counts_72h": {
    "D:DRONE_UAS": 1,
    "D:INCIDENT": 1,
    "D:INFRA_CI": 77,
    "D:NEWS_INTEL": 95,
    "D:SECURITY_CRIME": 3
  },
  "domain_counts_72h_deduped": {
    "D:DRONE_UAS": 1,
    "D:INCIDENT": 1,
    "D:INFRA_CI": 77,
    "D:NEWS_INTEL": 95,
    "D:SECURITY_CRIME": 3
  },
  "region_counts_72h": {
    "REG:EUROPE": 59,
    "REG:GLOBAL": 30,
    "REG:MEDITERRANEAN": 1,
    "REG:NORTH_SEA": 12,
    "REG:OTHER": 24,
    "REG:UNKNOWN": 51
  },
  "region_counts_72h_deduped": {
    "REG:EUROPE": 59,
    "REG:GLOBAL": 30,
    "REG:MEDITERRANEAN": 1,
    "REG:NORTH_SEA": 12,
    "REG:OTHER": 24,
    "REG:UNKNOWN": 51
  },
  "baseline_observations": {
    "note": "Raw baseline observations for later 90-day normalization. Scores are not yet baseline-normalized.",
    "source_kind_counts_bucket": {},
    "source_kind_counts_bucket_deduped": {},
    "source_kind_counts_72h": {
      "rss": 174,
      "social": 3
    },
    "source_kind_counts_72h_deduped": {
      "rss": 174,
      "social": 3
    },
    "source_domain_counts_bucket": {},
    "source_domain_counts_bucket_deduped": {},
    "source_domain_counts_72h": {
      "atlantic_council_reports|D:INFRA_CI": 9,
      "cepa_feed|D:INFRA_CI": 13,
      "die_flaschenpost_aussenpolitik_rss|D:INFRA_CI": 10,
      "gcaptain_rss|D:NEWS_INTEL": 23,
      "gCaptain|D:NEWS_INTEL": 7,
      "gids_feed|D:INFRA_CI": 10,
      "rusi_latest_commentary|D:INFRA_CI": 5,
      "rusi_latest_publications|D:INFRA_CI": 9,
      "small_wars_journal_rss|D:NEWS_INTEL": 30,
      "swp_publications_de|D:INFRA_CI": 8,
      "swp_publications_en|D:INFRA_CI": 5,
      "The Maritime Executive|D:DRONE_UAS": 1,
      "The Maritime Executive|D:INCIDENT": 1,
      "The Maritime Executive|D:INFRA_CI": 6,
      "The Maritime Executive|D:NEWS_INTEL": 35,
      "The Maritime Executive|D:SECURITY_CRIME": 2,
      "tom_sharpe_x|D:INFRA_CI": 2,
      "worldcrimeintel_x|D:SECURITY_CRIME": 1
    },
    "source_domain_counts_72h_deduped": {
      "atlantic_council_reports|D:INFRA_CI": 9,
      "cepa_feed|D:INFRA_CI": 13,
      "die_flaschenpost_aussenpolitik_rss|D:INFRA_CI": 10,
      "gcaptain_rss|D:NEWS_INTEL": 23,
      "gCaptain|D:NEWS_INTEL": 7,
      "gids_feed|D:INFRA_CI": 10,
      "rusi_latest_commentary|D:INFRA_CI": 5,
      "rusi_latest_publications|D:INFRA_CI": 9,
      "small_wars_journal_rss|D:NEWS_INTEL": 30,
      "swp_publications_de|D:INFRA_CI": 8,
      "swp_publications_en|D:INFRA_CI": 5,
      "The Maritime Executive|D:DRONE_UAS": 1,
      "The Maritime Executive|D:INCIDENT": 1,
      "The Maritime Executive|D:INFRA_CI": 6,
      "The Maritime Executive|D:NEWS_INTEL": 35,
      "The Maritime Executive|D:SECURITY_CRIME": 2,
      "tom_sharpe_x|D:INFRA_CI": 2,
      "worldcrimeintel_x|D:SECURITY_CRIME": 1
    },
    "source_region_counts_72h": {
      "atlantic_council_reports|REG:EUROPE": 9,
      "cepa_feed|REG:EUROPE": 13,
      "die_flaschenpost_aussenpolitik_rss|REG:EUROPE": 10,
      "gcaptain_rss|REG:OTHER": 23,
      "gCaptain|REG:UNKNOWN": 7,
      "gids_feed|REG:NORTH_SEA": 10,
      "rusi_latest_commentary|REG:EUROPE": 5,
      "rusi_latest_publications|REG:EUROPE": 9,
      "small_wars_journal_rss|REG:GLOBAL": 30,
      "swp_publications_de|REG:EUROPE": 8,
      "swp_publications_en|REG:EUROPE": 5,
      "The Maritime Executive|REG:MEDITERRANEAN": 1,
      "The Maritime Executive|REG:UNKNOWN": 44,
      "tom_sharpe_x|REG:NORTH_SEA": 2,
      "worldcrimeintel_x|REG:OTHER": 1
    },
    "source_region_counts_72h_deduped": {
      "atlantic_council_reports|REG:EUROPE": 9,
      "cepa_feed|REG:EUROPE": 13,
      "die_flaschenpost_aussenpolitik_rss|REG:EUROPE": 10,
      "gcaptain_rss|REG:OTHER": 23,
      "gCaptain|REG:UNKNOWN": 7,
      "gids_feed|REG:NORTH_SEA": 10,
      "rusi_latest_commentary|REG:EUROPE": 5,
      "rusi_latest_publications|REG:EUROPE": 9,
      "small_wars_journal_rss|REG:GLOBAL": 30,
      "swp_publications_de|REG:EUROPE": 8,
      "swp_publications_en|REG:EUROPE": 5,
      "The Maritime Executive|REG:MEDITERRANEAN": 1,
      "The Maritime Executive|REG:UNKNOWN": 44,
      "tom_sharpe_x|REG:NORTH_SEA": 2,
      "worldcrimeintel_x|REG:OTHER": 1
    },
    "duplicate_sources_bucket": {},
    "duplicate_sources_72h": {},
    "source_caps_bucket": [],
    "source_caps_72h": [
      {
        "source_id": "The Maritime Executive",
        "source_kind": "rss",
        "raw_events": 45,
        "weighted_events": 8.3,
        "capped_events": 44
      },
      {
        "source_id": "small_wars_journal_rss",
        "source_kind": "rss",
        "raw_events": 30,
        "weighted_events": 6.05,
        "capped_events": 29
      },
      {
        "source_id": "gcaptain_rss",
        "source_kind": "rss",
        "raw_events": 23,
        "weighted_events": 5,
        "capped_events": 22
      },
      {
        "source_id": "cepa_feed",
        "source_kind": "rss",
        "raw_events": 13,
        "weighted_events": 3.5,
        "capped_events": 12
      },
      {
        "source_id": "die_flaschenpost_aussenpolitik_rss",
        "source_kind": "rss",
        "raw_events": 10,
        "weighted_events": 3.05,
        "capped_events": 9
      },
      {
        "source_id": "gids_feed",
        "source_kind": "rss",
        "raw_events": 10,
        "weighted_events": 3.05,
        "capped_events": 9
      },
      {
        "source_id": "atlantic_council_reports",
        "source_kind": "rss",
        "raw_events": 9,
        "weighted_events": 2.9,
        "capped_events": 8
      },
      {
        "source_id": "rusi_latest_publications",
        "source_kind": "rss",
        "raw_events": 9,
        "weighted_events": 2.9,
        "capped_events": 8
      },
      {
        "source_id": "swp_publications_de",
        "source_kind": "rss",
        "raw_events": 8,
        "weighted_events": 2.75,
        "capped_events": 7
      },
      {
        "source_id": "gCaptain",
        "source_kind": "rss",
        "raw_events": 7,
        "weighted_events": 2.6,
        "capped_events": 6
      },
      {
        "source_id": "rusi_latest_commentary",
        "source_kind": "rss",
        "raw_events": 5,
        "weighted_events": 2.3,
        "capped_events": 4
      },
      {
        "source_id": "swp_publications_en",
        "source_kind": "rss",
        "raw_events": 5,
        "weighted_events": 2.3,
        "capped_events": 4
      },
      {
        "source_id": "tom_sharpe_x",
        "source_kind": "social",
        "raw_events": 2,
        "weighted_events": 1.45,
        "capped_events": 1
      },
      {
        "source_id": "worldcrimeintel_x",
        "source_kind": "social",
        "raw_events": 1,
        "weighted_events": 1,
        "capped_events": 0
      }
    ]
  }
}
